odoo/addons/website_disable_lang_menu/README.rst
odoo/addons/website_disable_lang_menu/__init__.py
odoo/addons/website_disable_lang_menu/__manifest__.py
odoo/addons/website_disable_lang_menu/models/__init__.py
odoo/addons/website_disable_lang_menu/models/ir_ui_view.py
odoo/addons/website_disable_lang_menu/models/res_config_settings.py
odoo/addons/website_disable_lang_menu/models/website.py
odoo/addons/website_disable_lang_menu/static/description/icon.png
odoo/addons/website_disable_lang_menu/views/res_config_settings_views.xml
odoo13_addon_website_disable_lang_menu-13.0.1.0.1.dev2.dist-info/METADATA
odoo13_addon_website_disable_lang_menu-13.0.1.0.1.dev2.dist-info/WHEEL
odoo13_addon_website_disable_lang_menu-13.0.1.0.1.dev2.dist-info/top_level.txt
odoo13_addon_website_disable_lang_menu-13.0.1.0.1.dev2.dist-info/RECORD
